axiomatic_pic/__init__.py
axiomatic_pic-0.1.9.dist-info/METADATA
axiomatic_pic-0.1.9.dist-info/WHEEL
axiomatic_pic-0.1.9.dist-info/top_level.txt
axiomatic_pic-0.1.9.dist-info/RECORD
