Metadata-Version: 2.1
Name: axiomatic_pic
Version: 0.1.9
Summary: Axiomatic PIC magic assistant
Home-page: https://www.axiomatic-ai.com
Author: Leopoldo S.
Author-email: leopoldo@axiomatic-ai.com
License: MIT
Keywords: PIC,Axiomatic,AI
Classifier: Development Status :: 3 - Alpha
Classifier: Intended Audience :: Developers
Classifier: Framework :: IPython
Classifier: Programming Language :: Python :: 3
Classifier: Topic :: Software Development :: Libraries :: Python Modules
Requires-Dist: axiomatic
Requires-Dist: ipython
Requires-Dist: platformdirs
